flexi_dict/__init__.py
flexi_dict/config.py
flexi_dict/flexi_dict.py
flexi_dict/utils.py
flexi_dict/flexi_trie/__init__.py
flexi_dict/flexi_trie/flexi_trie.py
flexi_dict/flexi_trie/flexi_trie_traverser.py
flexi_dict/search_engine/__init__.py
flexi_dict/search_engine/correction.py
flexi_dict/search_engine/correction_detail.py
flexi_dict/search_engine/fuzzy_search_result.py
flexi_dict/search_engine/search_engine.py
flexi_dict/search_engine/search_state.py
numeral_converter/__init__.py
numeral_converter/config.py
numeral_converter/numeral_converter.py
numeral_converter/numeral_converter_helpers.py
numeral_converter/numeral_converter_loader.py
numeral_converter/numeral_preprocessor.py
numeral_converter/patterns.py
numeral_converter/text.py
numeral_converter/numeral_data_collector/__init__.py
numeral_converter/numeral_data_collector/numeral_data_cointainer.py
numeral_converter/numeral_data_collector/numeral_data_collector.py
numeral_converter/numeral_data_collector/flexi_index_builder/__init__.py
numeral_converter/numeral_data_collector/flexi_index_builder/flexi_index_builder.py
numeral_converter/numeral_data_collector/numeral_data_loader/__init__.py
numeral_converter/numeral_data_collector/numeral_data_loader/numeral_data.py
numeral_converter/numeral_data_collector/numeral_data_loader/numeral_data_loader.py
numeral_converter/numeral_data_collector/numeral_data_loader/numeral_entry.py
numeral_converter/numeral_data_collector/numeral_data_loader/utils.py
numeral_converter/resource/__init__.py
numeral_converter/resource/en.csv
numeral_converter/resource/ru.csv
numeral_converter/resource/uk.csv
nlp_flexi_tools-0.1.0.dist-info/LICENSE
nlp_flexi_tools-0.1.0.dist-info/METADATA
nlp_flexi_tools-0.1.0.dist-info/WHEEL
nlp_flexi_tools-0.1.0.dist-info/top_level.txt
nlp_flexi_tools-0.1.0.dist-info/RECORD
