Metadata-Version: 2.1
Name: nlp-flexi-tools
Version: 0.1.0
Summary: NLP toolkit based on the flexi-dict data structure, designed for efficient fuzzy search, with a focus on simplicity, performance, and flexibility.
Home-page: UNKNOWN
Author: Tetiana Lytvynenko
Author-email: lytvynenkotv@gmail.com
License: MIT
Keywords: fuzzy search,nlp tools,flexi search,numeral converter
Platform: UNKNOWN
Classifier: Programming Language :: Python :: 3
Classifier: License :: OSI Approved :: MIT License
Classifier: Operating System :: OS Independent
Requires-Python: >=3.11
Requires-Dist: dill (<0.4,>=0.3.9)
Requires-Dist: pandas (<2.3,>=2.2.3)
